jupyter_collaboration_ui/__init__.py
jupyter_collaboration_ui/_version.py
jupyter_collaboration_ui-2.1.2.data/data/share/jupyter/labextensions/@jupyter/collaboration-extension/package.json
jupyter_collaboration_ui-2.1.2.data/data/share/jupyter/labextensions/@jupyter/collaboration-extension/schemas/@jupyter/collaboration-extension/package.json.orig
jupyter_collaboration_ui-2.1.2.data/data/share/jupyter/labextensions/@jupyter/collaboration-extension/schemas/@jupyter/collaboration-extension/shared-link.json
jupyter_collaboration_ui-2.1.2.data/data/share/jupyter/labextensions/@jupyter/collaboration-extension/schemas/@jupyter/collaboration-extension/user-menu-bar.json
jupyter_collaboration_ui-2.1.2.data/data/share/jupyter/labextensions/@jupyter/collaboration-extension/static/240.61d3aa702c2fa861c087.js
jupyter_collaboration_ui-2.1.2.data/data/share/jupyter/labextensions/@jupyter/collaboration-extension/static/393.f5e8288bb3ed18ac084a.js
jupyter_collaboration_ui-2.1.2.data/data/share/jupyter/labextensions/@jupyter/collaboration-extension/static/422.c33fd4bf2f8b13b1f430.js
jupyter_collaboration_ui-2.1.2.data/data/share/jupyter/labextensions/@jupyter/collaboration-extension/static/444.d6f3cc1c6d4b374efa63.js
jupyter_collaboration_ui-2.1.2.data/data/share/jupyter/labextensions/@jupyter/collaboration-extension/static/784.586f70cab201cb43c954.js
jupyter_collaboration_ui-2.1.2.data/data/share/jupyter/labextensions/@jupyter/collaboration-extension/static/842.6243a771ad51bd0bf3f3.js
jupyter_collaboration_ui-2.1.2.data/data/share/jupyter/labextensions/@jupyter/collaboration-extension/static/944.27191c0195c19b79d6b0.js
jupyter_collaboration_ui-2.1.2.data/data/share/jupyter/labextensions/@jupyter/collaboration-extension/static/952.8934cdeb03f9bd1e666f.js
jupyter_collaboration_ui-2.1.2.data/data/share/jupyter/labextensions/@jupyter/collaboration-extension/static/remoteEntry.6a2662a819e4bd4f72ae.js
jupyter_collaboration_ui-2.1.2.dist-info/METADATA
jupyter_collaboration_ui-2.1.2.dist-info/WHEEL
jupyter_collaboration_ui-2.1.2.dist-info/licenses/LICENSE
jupyter_collaboration_ui-2.1.2.dist-info/RECORD
